jupyterlab_apibaker/__init__.py
jupyterlab_apibaker/_version.py
jupyterlab_apibaker/api_code_variables.py
jupyterlab_apibaker/api_collection_handler.py
jupyterlab_apibaker/apikey_handler.py
jupyterlab_apibaker/custom_encoder.py
jupyterlab_apibaker/custom_exceptions.py
jupyterlab_apibaker/custom_types.py
jupyterlab_apibaker/endpoint_handler.py
jupyterlab_apibaker/handlers.py
jupyterlab_apibaker/notebook_handler.py
jupyterlab_apibaker/refresh_apikey_handler.py
jupyterlab_apibaker/system_handler.py
jupyterlab_apibaker/updates_handler.py
jupyterlab_apibaker/version_handler.py
jupyterlab_apibaker/workflow_log_handler.py
jupyterlab_apibaker/workflows_handler.py
jupyterlab_apibaker/common/__init__.py
jupyterlab_apibaker/common/requests_utils.py
jupyterlab_apibaker/common/variables.py
jupyterlab_apibaker/tests/__init__.py
jupyterlab_apibaker/tests/test_handlers.py
jupyterlab_apibaker-0.1.15.data/data/etc/jupyter/jupyter_server_config.d/jupyterlab_apibaker.json
jupyterlab_apibaker-0.1.15.data/data/share/jupyter/labextensions/jupyterlab-apibaker/build_log.json
jupyterlab_apibaker-0.1.15.data/data/share/jupyter/labextensions/jupyterlab-apibaker/package.json
jupyterlab_apibaker-0.1.15.data/data/share/jupyter/labextensions/jupyterlab-apibaker/static/lib_index_js.650d82927e1e52e98751.js
jupyterlab_apibaker-0.1.15.data/data/share/jupyter/labextensions/jupyterlab-apibaker/static/lib_index_js.650d82927e1e52e98751.js.map
jupyterlab_apibaker-0.1.15.data/data/share/jupyter/labextensions/jupyterlab-apibaker/static/node_modules_babel_runtime_helpers_esm_extends_js-_f05a0.771048910064478ce0f7.js
jupyterlab_apibaker-0.1.15.data/data/share/jupyter/labextensions/jupyterlab-apibaker/static/node_modules_babel_runtime_helpers_esm_extends_js-_f05a0.771048910064478ce0f7.js.map
jupyterlab_apibaker-0.1.15.data/data/share/jupyter/labextensions/jupyterlab-apibaker/static/node_modules_babel_runtime_helpers_esm_extends_js-_f05a1.8e57d5c6228ff3d4f7e6.js
jupyterlab_apibaker-0.1.15.dist-info/METADATA
jupyterlab_apibaker-0.1.15.dist-info/WHEEL
jupyterlab_apibaker-0.1.15.dist-info/licenses/LICENSE
jupyterlab_apibaker-0.1.15.dist-info/RECORD
