Metadata-Version: 2.3
Name: jupyterlab_apibaker
Version: 0.1.15
Summary: Create a secured API based on a function in your notebook in a few clicks.
Project-URL: Homepage, https://github.com/Navteca/jupyterlab-apibaker
Project-URL: Bug Tracker, https://github.com/Navteca/jupyterlab-apibaker/issues
Project-URL: Repository, https://github.com/Navteca/jupyterlab-apibaker.git
Author-email: Team Navteca <team@navteca.com>
License: BSD 3-Clause License
License-File: LICENSE
Classifier: Framework :: Jupyter
Classifier: Framework :: Jupyter :: JupyterLab
Classifier: Framework :: Jupyter :: JupyterLab :: 4
Classifier: Framework :: Jupyter :: JupyterLab :: Extensions
Classifier: Framework :: Jupyter :: JupyterLab :: Extensions :: Prebuilt
Classifier: License :: OSI Approved :: BSD License
Classifier: Programming Language :: Python
Classifier: Programming Language :: Python :: 3
Classifier: Programming Language :: Python :: 3.8
Classifier: Programming Language :: Python :: 3.9
Classifier: Programming Language :: Python :: 3.10
Classifier: Programming Language :: Python :: 3.11
Classifier: Programming Language :: Python :: 3.12
Requires-Python: >=3.8
Requires-Dist: dataclass-wizard>=0.22.3
Requires-Dist: jupyter-server<3,>=2.0.1
Requires-Dist: pytablewriter
Provides-Extra: test
Requires-Dist: coverage; extra == 'test'
Requires-Dist: pytest; extra == 'test'
Requires-Dist: pytest-asyncio; extra == 'test'
Requires-Dist: pytest-cov; extra == 'test'
Requires-Dist: pytest-jupyter[server]>=0.6.0; extra == 'test'
